Workbook
Name aporte: APP!$D$11
Name patrimonio: APP!$D$14
Name qtd_anos: APP!$D$12
Name rendimento_carteira: APP!$D$7
Name salario: APP!$D$6
Name sugestao_investimento: APP!$D$8
Name taxa_mensal: APP!$D$13

Sheet APP
B2: SIMULADOR DE INVESTIMENTOS EM FIIs
B3: Planeje aportes, estime o patrimônio futuro e visualize uma divisão ilustrativa por perfil.
B5: CONFIGURAÇÕES
B6: Salário | D6: 2000
B7: Rendimento Carteira | D7: 0.006
B8: Sugestão de Investimento (30%) | D8: =D6*30% -> 600
B10: INVESTIMENTO MENSAL
B11: Quanto investir por mês ? | D11: 750
B12: Por Quantos Anos ? | D12: 5
B13: Taxa de Rendimento mensal ? | D13: 0.01079
B14: Patrimônio acumulado ? | D14: =FV(taxa_mensal,qtd_anos*12,aporte*-1) -> 62832.685
B15: Dividendos Mensais ? | D15: =patrimonio*rendimento_carteira -> 376.99611
B17: Cenários | D17: Dividendo
A18: 2 | B18: Quanto em 2 Anos ? | C18: =FV($D$13,$A18*12,$D$11*-1) -> 20420.72 | D18: =C18*rendimento_carteira -> 122.52432
A19: 5 | B19: Quanto em 5 Anos ? | C19: =FV($D$13,$A19*12,$D$11*-1) -> 62832.685 | D19: =C19*rendimento_carteira -> 376.99611
A20: 10 | B20: Quanto em 10 Anos ? | C20: =FV($D$13,$A20*12,$D$11*-1) -> 182463.16 | D20: =C20*rendimento_carteira -> 1094.779
A21: 20 | B21: Quanto em 20 Anos ? | C21: =FV($D$13,$A21*12,$D$11*-1) -> 843898.8 | D21: =C21*rendimento_carteira -> 5063.3928
A22: 30 | B22: Quanto em 30 Anos ? | C22: =FV($D$13,$A22*12,$D$11*-1) -> 3241627.2 | D22: =C22*rendimento_carteira -> 19449.763
B25: PERFIL | D25: Moderado
B26: VALOR A SER INVESTIDO POR MÊS | D26: =aporte -> 750
B28: TIPO DE FII | C28: Percentual Sugerido | D28: Valores
B29: PAPEL | C29: =VLOOKUP($D$25&"-"&B29,Planilha2!$A:$D,4,FALSE) -> 0.32 | D29: =C29*$D$26 -> 240
B30: TIJOLO | C30: =VLOOKUP($D$25&"-"&B30,Planilha2!$A:$D,4,FALSE) -> 0.35 | D30: =C30*$D$26 -> 262.5
B31: HÍBRIDOS | C31: =VLOOKUP($D$25&"-"&B31,Planilha2!$A:$D,4,FALSE) -> 0.08 | D31: =C31*$D$26 -> 60
B32: FOFs | C32: =VLOOKUP($D$25&"-"&B32,Planilha2!$A:$D,4,FALSE) -> 0.05 | D32: =C32*$D$26 -> 37.5
B33: DESENVOLVIMENTO | C33: =VLOOKUP($D$25&"-"&B33,Planilha2!$A:$D,4,FALSE) -> 0.1 | D33: =C33*$D$26 -> 75
B34: HOTELARIAS | C34: =VLOOKUP($D$25&"-"&B34,Planilha2!$A:$D,4,FALSE) -> 0.1 | D34: =C34*$D$26 -> 75
B35: TOTAL DO APORTE | C35: =SUM(C29:C34) -> 1 | D35: =SUM(D29:D34) -> 750

Sheet Planilha2
A2: CHAVE | B2: PERFIL | C2: TIPO DE FII | D2: % | G2: EXEMPLO DE BUSCA
A3: =B3&"-"&C3 -> Conservador-PAPEL | B3: Conservador | C3: PAPEL | D3: 0.3 | H3: %
A4: =B4&"-"&C4 -> Conservador-TIJOLO | B4: Conservador | C4: TIJOLO | D4: 0.5 | G4: Moderado-TIJOLO | H4: =VLOOKUP(G4,$A:$D,4,FALSE) -> 0.35
A5: =B5&"-"&C5 -> Conservador-HÍBRIDOS | B5: Conservador | C5: HÍBRIDOS | D5: 0.1
A6: =B6&"-"&C6 -> Conservador-FOFs | B6: Conservador | C6: FOFs | D6: 0.1
A7: =B7&"-"&C7 -> Conservador-DESENVOLVIMENTO | B7: Conservador | C7: DESENVOLVIMENTO | D7: 0
A8: =B8&"-"&C8 -> Conservador-HOTELARIAS | B8: Conservador | C8: HOTELARIAS | D8: 0
A9: =B9&"-"&C9 -> Moderado-PAPEL | B9: Moderado | C9: PAPEL | D9: 0.32
A10: =B10&"-"&C10 -> Moderado-TIJOLO | B10: Moderado | C10: TIJOLO | D10: 0.35
A11: =B11&"-"&C11 -> Moderado-HÍBRIDOS | B11: Moderado | C11: HÍBRIDOS | D11: 0.08
A12: =B12&"-"&C12 -> Moderado-FOFs | B12: Moderado | C12: FOFs | D12: 0.05
A13: =B13&"-"&C13 -> Moderado-DESENVOLVIMENTO | B13: Moderado | C13: DESENVOLVIMENTO | D13: 0.1
A14: =B14&"-"&C14 -> Moderado-HOTELARIAS | B14: Moderado | C14: HOTELARIAS | D14: 0.1
A15: =B15&"-"&C15 -> Agressivo-PAPEL | B15: Agressivo | C15: PAPEL | D15: 0.5
A16: =B16&"-"&C16 -> Agressivo-TIJOLO | B16: Agressivo | C16: TIJOLO | D16: 0.1
... A20: =B20&"-"&C20 -> Agressivo-HOTELARIAS | B20: Agressivo | C20: HOTELARIAS | D20: 0.1
F22: Observação:
F23: Percentuais ilustrativos para fins educacionais; não são recomendação de investimento.
